dbseeder/__init__.py
dbseeder/__main__.py
dbseeder/database.py
dbseeder/fields.py
dbseeder/table.py
dbseeder-0.0.4.3.dist-info/LICENSE
dbseeder-0.0.4.3.dist-info/METADATA
dbseeder-0.0.4.3.dist-info/WHEEL
dbseeder-0.0.4.3.dist-info/top_level.txt
dbseeder-0.0.4.3.dist-info/RECORD
