Metadata-Version: 2.1
Name: dbseeder
Version: 0.0.4.3
Summary: A package to make seeds for some relational databases
Author-email: Long Pham <phamlong15297@gmail.com>
Project-URL: Homepage, https://github.com/conlacda/auto-seeder
Project-URL: Bug Tracker, https://github.com/conlacda/auto-seeder/issues
Classifier: Programming Language :: Python :: 3
Classifier: License :: OSI Approved :: MIT License
Classifier: Operating System :: OS Independent
Requires-Python: >=3.7
License-File: LICENSE
